MANIFEST.in
NEWS
README.rst
recodemodule.c
setup.py
testsuite.py
python_recode.egg-info/PKG-INFO
python_recode.egg-info/SOURCES.txt
python_recode.egg-info/dependency_links.txt
python_recode.egg-info/top_level.txt